news_mcp_server/__init__.py
news_mcp_server/cli.py
news_mcp_server/main.py
news_mcp_server/api/client.py
news_mcp_server/cache/__init__.py
news_mcp_server/cache/manager.py
news_mcp_server/cache/providers.py
news_mcp_server/core/config.py
news_mcp_server/core/models.py
news_mcp_server/core/server.py
news_mcp_server/monitoring/__init__.py
news_mcp_server/monitoring/alerting.py
news_mcp_server/monitoring/health.py
news_mcp_server/monitoring/metrics.py
news_mcp_server/plugins/__init__.py
news_mcp_server/plugins/autogpt.py
news_mcp_server/plugins/base.py
news_mcp_server/plugins/crewai.py
news_mcp_server/plugins/langchain.py
news_mcp_server/plugins/manager.py
news_mcp_server/utils/__init__.py
news_mcp_server/utils/formatters.py
news_mcp_server/utils/helpers.py
news_mcp_server/utils/validators.py
news_mcp_server-1.0.0.dist-info/METADATA
news_mcp_server-1.0.0.dist-info/WHEEL
news_mcp_server-1.0.0.dist-info/entry_points.txt
news_mcp_server-1.0.0.dist-info/licenses/LICENSE
news_mcp_server-1.0.0.dist-info/RECORD
