Metadata-Version: 2.4
Name: news-mcp-server
Version: 1.0.0
Summary: Hybrid MCP server for news aggregation with Press Monitor integration
Project-URL: Homepage, https://github.com/yourorg/news-mcp-server
Project-URL: Documentation, https://docs.yourorg.com/news-mcp-server
Project-URL: Repository, https://github.com/yourorg/news-mcp-server
Project-URL: Issues, https://github.com/yourorg/news-mcp-server/issues
Author-email: Your Organization <dev@yourorg.com>
License: MIT
License-File: LICENSE
Keywords: agents,ai,mcp,news,press-monitor
Classifier: Development Status :: 4 - Beta
Classifier: Intended Audience :: Developers
Classifier: License :: OSI Approved :: MIT License
Classifier: Programming Language :: Python :: 3
Classifier: Programming Language :: Python :: 3.8
Classifier: Programming Language :: Python :: 3.9
Classifier: Programming Language :: Python :: 3.10
Classifier: Programming Language :: Python :: 3.11
Classifier: Programming Language :: Python :: 3.12
Classifier: Topic :: Internet :: WWW/HTTP :: HTTP Servers
Classifier: Topic :: Software Development :: Libraries :: Python Modules
Requires-Python: >=3.8
Requires-Dist: anyio>=3.7.0
Requires-Dist: click>=8.1.0
Requires-Dist: fastapi>=0.104.0
Requires-Dist: httpx>=0.25.0
Requires-Dist: prometheus-client>=0.17.0
Requires-Dist: pydantic-settings>=2.0.0
Requires-Dist: pydantic>=2.4.0
Requires-Dist: python-json-logger>=2.0.0
Requires-Dist: redis>=5.0.0
Requires-Dist: uvicorn[standard]>=0.24.0
Provides-Extra: all
Requires-Dist: azure-identity>=1.12.0; extra == 'all'
Requires-Dist: boto3>=1.26.0; extra == 'all'
Requires-Dist: google-cloud-core>=2.3.0; extra == 'all'
Requires-Dist: langchain-community>=0.0.10; extra == 'all'
Requires-Dist: langchain>=0.1.0; extra == 'all'
Requires-Dist: prometheus-client>=0.17.0; extra == 'all'
Requires-Dist: psutil>=5.9.0; extra == 'all'
Requires-Dist: redis>=5.0.0; extra == 'all'
Provides-Extra: cloud
Requires-Dist: azure-identity>=1.12.0; extra == 'cloud'
Requires-Dist: boto3>=1.26.0; extra == 'cloud'
Requires-Dist: google-cloud-core>=2.3.0; extra == 'cloud'
Provides-Extra: dev
Requires-Dist: black>=23.0.0; extra == 'dev'
Requires-Dist: flake8>=6.0.0; extra == 'dev'
Requires-Dist: isort>=5.12.0; extra == 'dev'
Requires-Dist: mypy>=1.5.0; extra == 'dev'
Requires-Dist: pre-commit>=3.4.0; extra == 'dev'
Requires-Dist: pytest-asyncio>=0.21.0; extra == 'dev'
Requires-Dist: pytest-cov>=4.1.0; extra == 'dev'
Requires-Dist: pytest>=7.4.0; extra == 'dev'
Provides-Extra: frameworks
Requires-Dist: langchain-community>=0.0.10; extra == 'frameworks'
Requires-Dist: langchain>=0.1.0; extra == 'frameworks'
Provides-Extra: full
Requires-Dist: prometheus-client>=0.17.0; extra == 'full'
Requires-Dist: psutil>=5.9.0; extra == 'full'
Requires-Dist: redis>=5.0.0; extra == 'full'
Provides-Extra: minimal
